Metadata-Version: 2.1
Name: stat-prob
Version: 1.0
Summary: Gaussian and Binomial distributions
Author: Antonio Nebres
Author-email: anebres.ubiqus@gmail.com
